Metadata-Version: 2.1
Name: usd_lde
Version: 0.0.1
Summary: My Package
Author-email: your@domain.com
